Metadata-Version: 2.1
Name: streamlit-endpoint-patch
Version: 0.1.0
Summary: Restores old endpoints prior to streamlit==1.18.0
Home-page: https://github.com/joy13975/streamlit-endpoint-patch
Author: Joy Yeh
Author-email: joyyeh.tw@gmail.com
License: Apache 2.0
Classifier: License :: OSI Approved :: MIT License
Classifier: Programming Language :: Python
Classifier: Programming Language :: Python :: 3
Classifier: Programming Language :: Python :: 3.6
Classifier: Programming Language :: Python :: Implementation :: CPython
Classifier: Programming Language :: Python :: Implementation :: PyPy
Requires-Python: >=3.7, !=3.9.7
License-File: LICENSE
